{
    "ac_index": {
        "01_BB_540": 67,
        "01_BB_545": 288,
        "01_BB_546": 287,
        "01_BB_550": 131,
        "01_BB_550_1": 255,
        "01_BB_550_2": 254,
        "01_BB_560": 132,
        "01_BB_590": 133,
        "01_BB_630": 113,
        "01_BB_670": 184,
        "01_BB_680": 185,
        "01_BB_730": 147,
        "01_BB_755": 189,
        "01_BB_760": 190,
        "01_BB_765": 175,
        "01_BB_766": 218,
        "01_BB_770": 42,
        "01_BB_775": 243,
        "01_HOOFD_010": 2,
        "01_HOOFD_011": 137,
        "01_HOOFD_012": 171,
        "01_HOOFD_015": 4,
        "01_HOOFD_020": 5,
        "01_HOOFD_030_1": 6,
        "01_HOOFD_030_2": 3,
        "01_HOOFD_040": 7,
        "01_HOOFD_050": 18,
        "01_HOOFD_055": 130,
        "01_HOOFD_060": 8,
        "01_HOOFD_061": 203,
        "01_HOOFD_065_0": 290,
        "01_HOOFD_065_1": 9,
        "01_HOOFD_065_2": 11,
        "01_HOOFD_080": 1,
        "01_HOOFD_090": 71,
        "01_HOOFD_099": 205,
        "01_HOOFD_100": 10,
        "01_HOOFD_100_0": 302,
        "01_HOOFD_101": 106,
        "01_HOOFD_101b": 307,
        "01_HOOFD_110": 13,
        "01_HOOFD_110_0": 291,
        "01_HOOFD_110_1": 204,
        "01_HOOFD_110_2": 201,
        "01_HOOFD_120": 14,
        "01_HOOFD_130": 15,
        "01_HOOFD_180": 17,
        "01_HOOFD_190": 129,
        "01_HOOFD_190_1": 23,
        "01_HOOFD_190_2": 22,
        "01_HOOFD_191": 165,
        "01_HOOFD_192": 166,
        "01_HOOFD_193": 167,
        "01_HOOFD_195": 127,
        "01_HOOFD_195_1": 72,
        "01_HOOFD_195_2": 41,
        "01_HOOFD_196": 208,
        "01_HOOFD_200": 25,
        "01_HOOFD_205": 24,
        "01_HOOFD_210_0": 314,
        "01_HOOFD_210_1": 143,
        "01_HOOFD_210_2": 144,
        "01_HOOFD_250": 27,
        "01_HOOFD_250_1": 206,
        "01_HOOFD_250_2": 207,
        "01_HOOFD_260": 28,
        "01_HOOFD_270": 26,
        "01_HOOFD_330": 89,
        "01_HOOFD_332": 271,
        "01_HOOFD_350_0": 293,
        "01_HOOFD_350_1": 105,
        "01_HOOFD_350_2": 103,
        "01_HOOFD_370": 30,
        "01_HOOFD_375": 31,
        "01_HOOFD_380": 32,
        "01_HOOFD_390": 82,
        "01_HOOFD_400": 83,
        "01_HOOFD_410_1": 84,
        "01_HOOFD_420": 85,
        "01_HOOFD_430": 33,
        "01_HOOFD_440_1": 54,
        "01_HOOFD_440_1a": 296,
        "01_HOOFD_440_2": 55,
        "01_HOOFD_445": 58,
        "01_HOOFD_446": 136,
        "01_HOOFD_446_0": 240,
        "01_HOOFD_447": 241,
        "01_HOOFD_450": 107,
        "01_HOOFD_451": 56,
        "01_HOOFD_455": 59,
        "01_HOOFD_459": 297,
        "01_HOOFD_460": 108,
        "01_HOOFD_460a": 228,
        "01_HOOFD_465": 60,
        "01_HOOFD_470": 34,
        "01_HOOFD_480": 36,
        "01_HOOFD_490_1": 35,
        "01_HOOFD_490_1a": 299,
        "01_HOOFD_490_2": 37,
        "01_HOOFD_490_3": 21,
        "01_HOOFD_490_4": 209,
        "01_HOOFD_490_5": 104,
        "01_HOOFD_490_5a": 215,
        "01_HOOFD_491": 139,
        "01_HOOFD_492_0": 238,
        "01_HOOFD_493": 239,
        "01_HOOFD_494a": 300,
        "01_HOOFD_495": 134,
        "01_HOOFD_500": 38,
        "01_HOOFD_505": 138,
        "01_HOOFD_510_0": 301,
        "01_HOOFD_510_1": 39,
        "01_HOOFD_510_2": 20,
        "01_HOOFD_510_2a": 214,
        "01_HOOFD_510_3": 224,
        "01_HOOFD_510_4": 216,
        "01_HOOFD_515": 223,
        "01_HOOFD_516": 219,
        "01_HOOFD_516a": 289,
        "01_HOOFD_519": 225,
        "01_HOOFD_520": 40,
        "01_HOOFD_530": 19,
        "01_HOOFD_530b": 331,
        "01_HOOFD_540": 88,
        "01_HOOFD_550": 93,
        "01_HOOFD_570": 94,
        "01_HOOFD_580_1": 95,
        "01_HOOFD_590": 116,
        "01_HOOFD_600_1": 117,
        "01_HOOFD_600_2": 114,
        "01_HOOFD_790": 51,
        "01_HOOFD_800": 124,
        "01_HOOFD_805": 148,
        "01_HOOFD_809": 317,
        "01_HOOFD_809c": 330,
        "01_HOOFD_810": 161,
        "01_HOOFD_811": 315,
        "01_HOOFD_814": 256,
        "01_HOOFD_815": 258,
        "01_HOOFD_820": 122,
        "01_OLO_120": 179,
        "01_OLO_140": 180,
        "01_OLO_160": 182,
        "01_OLO_180": 272,
        "01_OLO_190": 183,
        "01_OLO_240": 217,
        "02_DRZ_010": 163,
        "02_DRZ_011": 195,
        "02_DRZ_020_1": 191,
        "02_DRZ_020_2": 196,
        "02_DRZ_030_1": 192,
        "02_DRZ_035": 193,
        "02_OLO_100": 194,
        "03_GBH_005": 126,
        "03_VD_060_0": 304,
        "04_BPT_005": 97,
        "04_BPT_010": 68,
        "04_BPT_020": 69,
        "04_BPT_021": 211,
        "04_BPT_029": 210,
        "04_BPT_030": 70,
        "04_BPT_040": 74,
        "04_BPT_041": 321,
        "04_BPT_050": 181,
        "04_BPT_060": 75,
        "05_EIND_010": 16,
        "05_EIND_011": 329,
        "05_EIND_020": 57,
        "05_EIND_020_0": 294,
        "05_EIND_025": 322,
        "05_EIND_030_0": 295,
        "05_EIND_030_1": 52,
        "05_EIND_030_2": 120,
        "05_EIND_040": 53,
        "05_EIND_050": 121,
        "05_EIND_065": 170,
        "05_EIND_070": 66,
        "06_OLO_100": 188,
        "06_VD_010": 12,
        "06_VD_011": 282,
        "06_VD_012": 283,
        "06_VD_020": 91,
        "06_VD_020_1": 86,
        "06_VD_030": 43,
        "06_VD_030_1": 110,
        "06_VD_030_1a": 303,
        "06_VD_030_2": 109,
        "06_VD_030_3": 92,
        "06_VD_030_4": 231,
        "06_VD_030_5": 197,
        "06_VD_030_5a": 259,
        "06_VD_035": 232,
        "06_VD_040": 44,
        "06_VD_050": 45,
        "06_VD_060": 46,
        "06_VD_060_1": 169,
        "06_VD_060_2": 168,
        "06_VD_060_2a": 260,
        "06_VD_060_3": 233,
        "06_VD_060_4": 261,
        "06_VD_070": 87,
        "06_VD_100": 47,
        "06_VD_140": 48,
        "07_OPS_010": 128,
        "07_OPS_020": 198,
        "07_OPS_050": 200,
        "07_OPS_051": 318,
        "07_OPS_055": 199,
        "07_OPS_060_0": 319,
        "07_OPS_060_1": 145,
        "07_OPS_060_2": 146,
        "07_OPS_070": 221,
        "07_OPS_071": 220,
        "07_OPS_075": 324,
        "07_OPS_080_0": 323,
        "07_OPS_080_1": 222,
        "07_OPS_080_2": 187,
        "08_AWB45_005": 202,
        "08_AWB45_010": 49,
        "08_AWB45_020_0": 336,
        "08_AWB45_020_1": 50,
        "08_AWB45_020_2": 102,
        "08_AWB45_025": 235,
        "08_AWB45_030": 77,
        "08_AWB45_040": 90,
        "08_AWB45_045": 236,
        "08_AWB45_050": 237,
        "08_AWB45_051_0": 305,
        "08_AWB45_060": 78,
        "08_AWB45_070_1": 115,
        "08_AWB45_070_1a": 332,
        "08_AWB45_070_2": 79,
        "08_AWB45_070_3": 111,
        "08_AWB45_070_4": 248,
        "08_AWB45_070_5": 226,
        "08_AWB45_070_5a": 333,
        "08_AWB45_075": 249,
        "08_AWB45_080": 80,
        "08_AWB45_090_0": 320,
        "08_AWB45_090_1": 81,
        "08_AWB45_090_2": 112,
        "08_AWB45_090_2a": 306,
        "08_AWB45_090_3": 250,
        "08_AWB45_110": 118,
        "08_AWB45_115": 339,
        "08_AWB45_120_0": 340,
        "08_AWB45_140": 343,
        "08_AWB45_141": 344,
        "08_AWB45_142": 341,
        "08_AWB45_143_1": 342,
        "08_AWB45_143_2": 346,
        "08_AWB45_145": 345,
        "08_AWB45_150": 96,
        "08_AWB45_170": 76,
        "08_AWB45_175": 234,
        "08_AWB45_180": 119,
        "08_OLO_100": 176,
        "09_AH_I_010": 29,
        "09_AWB45_005": 164,
        "10_OLO_100": 273,
        "10_OLO_120": 274,
        "10_UOV_010": 61,
        "10_UOV_020": 62,
        "10_UOV_030": 101,
        "10_UOV_030a": 230,
        "10_UOV_035": 100,
        "10_UOV_039": 242,
        "10_UOV_040": 73,
        "10_UOV_045": 63,
        "10_UOV_050_0": 298,
        "10_UOV_050_1": 64,
        "10_UOV_050_2": 99,
        "10_UOV_050_2a": 229,
        "10_UOV_050_3": 246,
        "10_UOV_050_4": 227,
        "10_UOV_060": 65,
        "10_UOV_061": 284,
        "10_UOV_065": 154,
        "10_UOV_066": 153,
        "10_UOV_070": 151,
        "10_UOV_075": 172,
        "10_UOV_076": 173,
        "10_UOV_080": 150,
        "10_UOV_100": 152,
        "10_UOV_120": 149,
        "10_UOV_140": 155,
        "10_UOV_150": 156,
        "10_UOV_160": 157,
        "10_UOV_170": 158,
        "10_UOV_180": 123,
        "10_UOV_190": 159,
        "10_UOV_190_1": 212,
        "10_UOV_190_2": 213,
        "10_UOV_200": 160,
        "10_UOV_210": 98,
        "11_AH_II_010": 162,
        "11_AH_II_020": 245,
        "11_AH_II_030": 244,
        "11_AH_II_035": 251,
        "11_AH_II_036": 252,
        "11_AH_II_037_1": 253,
        "11_AH_II_037_2": 247,
        "11_AH_II_037_3": 277,
        "11_AH_II_040": 275,
        "11_AH_II_040_d": 338,
        "11_AH_II_040a": 337,
        "11_AH_II_040b": 327,
        "11_AH_II_040c": 316,
        "11_AH_II_060": 325,
        "11_AH_II_060b": 326,
        "11_AH_II_060c": 328,
        "11_AH_II_070_1": 276,
        "11_AH_II_070_2": 278,
        "11_AH_II_070_3": 334,
        "11_AH_II_070_3a": 335,
        "11_AH_II_130": 279,
        "11_AH_II_140": 280,
        "11_AH_II_145": 281,
        "12_AP_010": 186,
        "12_AP_011": 308,
        "12_AP_020_0": 309,
        "12_AP_020_1": 310,
        "12_AP_020_2": 262,
        "12_AP_025": 311,
        "12_AP_030": 312,
        "12_AP_040": 313,
        "12_AP_UOV_010": 174,
        "13_CRD_010": 292,
        "14_VRIJ_010": 125,
        "14_VRIJ_011": 266,
        "14_VRIJ_015": 177,
        "14_VRIJ_020_1": 141,
        "14_VRIJ_020_2": 140,
        "14_VRIJ_030": 178,
        "14_VRIJ_030_1": 267,
        "14_VRIJ_030_2": 268,
        "14_VRIJ_030_3": 257,
        "14_VRIJ_030_4": 263,
        "14_VRIJ_035": 142,
        "14_VRIJ_055": 269,
        "14_VRIJ_060_1": 265,
        "14_VRIJ_060_2": 264,
        "14_VRIJ_060_3": 270,
        "15_NGV_010": 135,
        "16_LGSD_010": 286,
        "16_LGSV_010": 285,
        "other": 400,
        "End": 347,
        "Start": 0
    },
    "dense_act": "linear",
    "generated_at": "08/05/2024 11:29:39",
    "start_simulation": "2010-06-28 10:00:00",
    "inter_mean_states": {
        "tasks": {
            "01_BB_540": 0.5991199629458083,
            "01_BB_630": 0.2679481241315424,
            "01_BB_730": 0.006947660954145438,
            "01_BB_765": 0.08360352014821677,
            "01_BB_770": 0.3441408059286707,
            "01_BB_775": 0.027559055118110236,
            "01_HOOFD_010": 0.19870310328855953,
            "01_HOOFD_011": 0.2809170912459472,
            "01_HOOFD_012": 0.0025474756831866605,
            "01_HOOFD_015": 0.11556276053728579,
            "01_HOOFD_020": 0.09309865678554886,
            "01_HOOFD_030_1": 0.09819360815192218,
            "01_HOOFD_030_2": 0.09008800370541918,
            "01_HOOFD_040": 0.10583603520148217,
            "01_HOOFD_050": 0.10375173691523853,
            "01_HOOFD_055": 0.027095877721167207,
            "01_HOOFD_060": 0.0856878184344604,
            "01_HOOFD_061": 0.012274201018990273,
            "01_HOOFD_065_1": 0.12992125984251968,
            "01_HOOFD_065_2": 0.2271885132005558,
            "01_HOOFD_080": 0.0002315886984715146,
            "01_HOOFD_090": 0.02616952292728115,
            "01_HOOFD_099": 0.009263547938860583,
            "01_HOOFD_100": 0.19245020842982863,
            "01_HOOFD_100_0": 0.0002315886984715146,
            "01_HOOFD_101": 0.15169059749884206,
            "01_HOOFD_101b": 0.0025474756831866605,
            "01_HOOFD_110": 0.19082908754052802,
            "01_HOOFD_110_1": 0.01366373320981936,
            "01_HOOFD_110_2": 0.013895321908290875,
            "01_HOOFD_120": 0.13270032422417785,
            "01_HOOFD_130": 0.06368689207966652,
            "01_HOOFD_180": 0.15470125057897174,
            "01_HOOFD_190": 0.028948587308939323,
            "01_HOOFD_190_1": 0.002779064381658175,
            "01_HOOFD_190_2": 0.0030106530801296896,
            "01_HOOFD_193": 0.0053265400648448355,
            "01_HOOFD_195": 0.0555812876331635,
            "01_HOOFD_196": 0.012505789717461788,
            "01_HOOFD_200": 0.09147753589624827,
            "01_HOOFD_205": 0.040064844835572024,
            "01_HOOFD_250": 0.06461324687355258,
            "01_HOOFD_250_1": 0.012042612320518759,
            "01_HOOFD_250_2": 0.012274201018990273,
            "01_HOOFD_260": 0.05789717461787865,
            "01_HOOFD_270": 0.02315886984715146,
            "01_HOOFD_330": 0.06577119036591014,
            "01_HOOFD_350_1": 0.00555812876331635,
            "01_HOOFD_350_2": 0.0002315886984715146,
            "01_HOOFD_370": 0.07063455303381196,
            "01_HOOFD_375": 0.07086614173228346,
            "01_HOOFD_380": 0.07225567392311255,
            "01_HOOFD_430": 0.058360352014821676,
            "01_HOOFD_440_1": 0.014358499305233904,
            "01_HOOFD_440_2": 0.08198239925891616,
            "01_HOOFD_445": 0.012968967114404817,
            "01_HOOFD_446": 0.0002315886984715146,
            "01_HOOFD_450": 0.0002315886984715146,
            "01_HOOFD_451": 0.013432144511347846,
            "01_HOOFD_455": 0.012968967114404817,
            "01_HOOFD_460": 0.07364520611394164,
            "01_HOOFD_465": 0.012968967114404817,
            "01_HOOFD_470": 0.03195924038906901,
            "01_HOOFD_480": 0.05465493283927744,
            "01_HOOFD_490_1": 0.055812876331635015,
            "01_HOOFD_490_1a": 0.0009263547938860583,
            "01_HOOFD_490_2": 0.06160259379342288,
            "01_HOOFD_490_3": 0.0935618341824919,
            "01_HOOFD_490_4": 0.009726725335803613,
            "01_HOOFD_490_5": 0.8626679018063919,
            "01_HOOFD_490_5a": 0.0009263547938860583,
            "01_HOOFD_491": 0.012968967114404817,
            "01_HOOFD_492_0": 0.0041685965724872626,
            "01_HOOFD_493": 0.0041685965724872626,
            "01_HOOFD_494a": 0.0009263547938860583,
            "01_HOOFD_495": 0.06299212598425197,
            "01_HOOFD_500": 0.01713756368689208,
            "01_HOOFD_505": 0.02871699861046781,
            "01_HOOFD_510_0": 0.0009263547938860583,
            "01_HOOFD_510_1": 0.09749884205650765,
            "01_HOOFD_510_2": 0.07271885132005558,
            "01_HOOFD_510_2a": 0.0009263547938860583,
            "01_HOOFD_510_3": 0.017369152385363594,
            "01_HOOFD_510_4": 0.017369152385363594,
            "01_HOOFD_515": 0.017832329782306623,
            "01_HOOFD_516": 0.16558591940713294,
            "01_HOOFD_519": 0.016905974988420565,
            "01_HOOFD_520": 0.0778138026864289,
            "01_HOOFD_530": 1.3371931449745253,
            "01_HOOFD_540": 0.048170449282075034,
            "01_HOOFD_790": 0.44974525243168134,
            "01_HOOFD_800": 0.5108846688281612,
            "01_HOOFD_805": 0.04863362667901806,
            "01_HOOFD_809": 0.0025474756831866605,
            "01_HOOFD_810": 0.2809170912459472,
            "01_HOOFD_811": 0.0025474756831866605,
            "01_HOOFD_814": 0.02732746641963872,
            "01_HOOFD_815": 0.15886984715145902,
            "01_HOOFD_820": 1.5660027790643816,
            "01_OLO_120": 0.002779064381658175,
            "01_OLO_140": 0.0025474756831866605,
            "01_OLO_160": 0.002779064381658175,
            "01_OLO_190": 0.003937007874015748,
            "01_OLO_240": 0.015748031496062992,
            "02_DRZ_010": 0.020379805465493284,
            "03_GBH_005": 0.06739231125521075,
            "04_BPT_005": 0.03751736915238536,
            "04_BPT_010": 0.02871699861046781,
            "04_BPT_020": 0.02825382121352478,
            "04_BPT_021": 0.003937007874015748,
            "04_BPT_029": 0.003937007874015748,
            "04_BPT_030": 0.028485409911996294,
            "04_BPT_040": 0.004863362667901806,
            "04_BPT_060": 0.004863362667901806,
            "05_EIND_010": 0.12042612320518759,
            "05_EIND_020": 0.0002315886984715146,
            "05_EIND_020_0": 0.0002315886984715146,
            "05_EIND_030_0": 0.0002315886984715146,
            "05_EIND_030_1": 0.0002315886984715146,
            "05_EIND_065": 0.10444650301065309,
            "06_VD_010": 0.3316350162112089,
            "06_VD_020": 0.028485409911996294,
            "06_VD_030_1": 0.030106530801296896,
            "06_VD_030_2": 0.01157943492357573,
            "06_VD_030_3": 0.02477999073645206,
            "06_VD_030_4": 0.003473830477072719,
            "06_VD_030_5": 0.0020842982862436313,
            "06_VD_035": 0.003242241778601204,
            "06_VD_060": 0.01968503937007874,
            "06_VD_060_1": 0.009263547938860583,
            "06_VD_060_2": 0.009031959240389069,
            "06_VD_060_3": 0.003242241778601204,
            "06_VD_070": 0.0009263547938860583,
            "07_OPS_010": 0.062297359888837424,
            "08_AWB45_005": 0.0699397869383974,
            "08_AWB45_010": 0.021306160259379342,
            "08_AWB45_020_1": 0.022464103751736915,
            "08_AWB45_020_2": 0.10490968040759611,
            "08_AWB45_030": 0.025474756831866605,
            "08_AWB45_040": 0.018527095877721167,
            "08_AWB45_060": 0.0025474756831866605,
            "08_AWB45_070_1": 0.002315886984715146,
            "08_AWB45_070_2": 0.0025474756831866605,
            "08_AWB45_070_3": 0.002315886984715146,
            "08_AWB45_080": 0.0002315886984715146,
            "08_AWB45_090_1": 0.0025474756831866605,
            "08_AWB45_090_2": 0.002315886984715146,
            "08_AWB45_110": 0.003242241778601204,
            "08_AWB45_150": 0.012737378415933302,
            "08_AWB45_175": 0.0013895321908290875,
            "08_AWB45_180": 0.006947660954145438,
            "09_AH_I_010": 0.07063455303381196,
            "09_AWB45_005": 0.06484483557202408,
            "10_UOV_010": 0.012968967114404817,
            "10_UOV_030": 0.03520148216767022,
            "10_UOV_030a": 0.0009263547938860583,
            "10_UOV_035": 0.014358499305233904,
            "10_UOV_040": 0.012737378415933302,
            "10_UOV_045": 0.012968967114404817,
            "10_UOV_050_1": 0.012968967114404817,
            "10_UOV_050_2": 0.003242241778601204,
            "10_UOV_060": 0.0013895321908290875,
            "10_UOV_180": 0.0002315886984715146,
            "10_UOV_210": 0.0002315886984715146,
            "11_AH_II_010": 0.026864289022695692,
            "11_AH_II_020": 0.0030106530801296896,
            "11_AH_II_030": 0.0030106530801296896,
            "11_AH_II_035": 0.0030106530801296896,
            "11_AH_II_036": 0.0030106530801296896,
            "11_AH_II_037_1": 0.0030106530801296896,
            "13_CRD_010": 0.0009263547938860583,
            "14_VRIJ_010": 0.04400185270958777,
            "14_VRIJ_030": 0.0002315886984715146,
            "14_VRIJ_030_3": 0.0002315886984715146,
            "15_NGV_010": 0.04307549791570171,
            "16_LGSD_010": 0.001157943492357573,
            "16_LGSV_010": 0.0037054191755442334,
            "other": 0,
            "End": 0.0,
            "Start": 0.0
        },
        "wip": 8.958314034275128
    },
    "l_size": 100,
    "log_size": 1012,
    "loss": 0.014777810778468847,
    "lstm_act": "selu",
    "n_size": 10,
    "optim": "Nadam",
    "roles": {
        "Role 1": [
            "560532",
            "560530"
        ],
        "Role 2": [
            "560458"
        ],
        "Role 3": [
            "560519"
        ],
        "Role 4": [
            "560521"
        ],
        "Role 5": [
            "560598"
        ],
        "Role 6": [
            "4634935"
        ]
    },
    "resources": [
        "560532",
        "560530",
        "560458",
        "560519",
        "560521",
        "560598",
        "4634935"
    ],
    "roles_table": [
        {
            "role": "Role 3",
            "task": "11_AH_II_036"
        },
        {
            "role": "Role 1",
            "task": "other"
        },
        {
            "role": "Role 1",
            "task": "05_EIND_030_1"
        },
        {
            "role": "Role 2",
            "task": "05_EIND_030_0"
        },
        {
            "role": "Role 2",
            "task": "05_EIND_020_0"
        },
        {
            "role": "Role 1",
            "task": "05_EIND_020"
        },
        {
            "role": "Role 4",
            "task": "01_HOOFD_250_1"
        },
        {
            "role": "Role 2",
            "task": "04_BPT_060"
        },
        {
            "role": "Role 2",
            "task": "04_BPT_040"
        },
        {
            "role": "Role 1",
            "task": "01_HOOFD_250_2"
        },
        {
            "role": "Role 3",
            "task": "06_VD_030_5"
        },
        {
            "role": "Role 1",
            "task": "01_HOOFD_190_1"
        },
        {
            "role": "Role 1",
            "task": "01_HOOFD_190_2"
        },
        {
            "role": "Role 2",
            "task": "01_HOOFD_193"
        },
        {
            "role": "Role 1",
            "task": "01_HOOFD_196"
        },
        {
            "role": "Role 1",
            "task": "01_HOOFD_350_1"
        },
        {
            "role": "Role 1",
            "task": "01_HOOFD_510_2a"
        },
        {
            "role": "Role 1",
            "task": "01_HOOFD_510_0"
        },
        {
            "role": "Role 3",
            "task": "11_AH_II_035"
        },
        {
            "role": "Role 1",
            "task": "01_HOOFD_494a"
        },
        {
            "role": "Role 1",
            "task": "01_HOOFD_490_1a"
        },
        {
            "role": "Role 1",
            "task": "01_HOOFD_493"
        },
        {
            "role": "Role 1",
            "task": "01_HOOFD_492_0"
        },
        {
            "role": "Role 1",
            "task": "01_HOOFD_450"
        },
        {
            "role": "Role 1",
            "task": "01_HOOFD_350_2"
        },
        {
            "role": "Role 2",
            "task": "01_OLO_240"
        },
        {
            "role": "Role 1",
            "task": "01_OLO_160"
        },
        {
            "role": "Role 1",
            "task": "01_OLO_140"
        },
        {
            "role": "Role 1",
            "task": "01_OLO_120"
        },
        {
            "role": "Role 3",
            "task": "11_AH_II_037_1"
        },
        {
            "role": "Role 1",
            "task": "13_CRD_010"
        },
        {
            "role": "Role 1",
            "task": "01_HOOFD_446"
        },
        {
            "role": "Role 1",
            "task": "01_HOOFD_490_5a"
        },
        {
            "role": "Role 1",
            "task": "08_AWB45_070_1"
        },
        {
            "role": "Role 1",
            "task": "08_AWB45_060"
        },
        {
            "role": "Role 2",
            "task": "10_UOV_040"
        },
        {
            "role": "Role 2",
            "task": "08_AWB45_070_2"
        },
        {
            "role": "Role 2",
            "task": "08_AWB45_070_3"
        },
        {
            "role": "Role 1",
            "task": "01_HOOFD_012"
        },
        {
            "role": "Role 2",
            "task": "08_AWB45_175"
        },
        {
            "role": "Role 1",
            "task": "08_AWB45_110"
        },
        {
            "role": "Role 2",
            "task": "08_AWB45_090_2"
        },
        {
            "role": "Role 1",
            "task": "08_AWB45_090_1"
        },
        {
            "role": "Role 2",
            "task": "08_AWB45_080"
        },
        {
            "role": "Role 3",
            "task": "11_AH_II_030"
        },
        {
            "role": "Role 3",
            "task": "11_AH_II_020"
        },
        {
            "role": "Role 1",
            "task": "10_UOV_210"
        },
        {
            "role": "Role 1",
            "task": "10_UOV_180"
        },
        {
            "role": "Role 4",
            "task": "14_VRIJ_030"
        },
        {
            "role": "Role 4",
            "task": "14_VRIJ_030_3"
        },
        {
            "role": "Role 6",
            "task": "08_AWB45_005"
        },
        {
            "role": "Role 4",
            "task": "01_HOOFD_100_0"
        },
        {
            "role": "Role 2",
            "task": "10_UOV_045"
        },
        {
            "role": "Role 1",
            "task": "16_LGSD_010"
        },
        {
            "role": "Role 1",
            "task": "01_HOOFD_080"
        },
        {
            "role": "Role 1",
            "task": "10_UOV_050_1"
        },
        {
            "role": "Role 1",
            "task": "10_UOV_010"
        },
        {
            "role": "Role 2",
            "task": "10_UOV_050_2"
        },
        {
            "role": "Role 3",
            "task": "06_VD_070"
        },
        {
            "role": "Role 3",
            "task": "06_VD_060_3"
        },
        {
            "role": "Role 2",
            "task": "06_VD_060"
        },
        {
            "role": "Role 3",
            "task": "06_VD_035"
        },
        {
            "role": "Role 3",
            "task": "06_VD_030_4"
        },
        {
            "role": "Role 2",
            "task": "08_AWB45_010"
        },
        {
            "role": "Role 1",
            "task": "05_EIND_065"
        },
        {
            "role": "Role 2",
            "task": "08_AWB45_020_1"
        },
        {
            "role": "Role 1",
            "task": "04_BPT_029"
        },
        {
            "role": "Role 1",
            "task": "01_OLO_190"
        },
        {
            "role": "Role 3",
            "task": "01_HOOFD_811"
        },
        {
            "role": "Role 3",
            "task": "01_HOOFD_809"
        },
        {
            "role": "Role 1",
            "task": "04_BPT_021"
        },
        {
            "role": "Role 1",
            "task": "16_LGSV_010"
        },
        {
            "role": "Role 2",
            "task": "01_HOOFD_440_1"
        },
        {
            "role": "Role 1",
            "task": "01_HOOFD_445"
        },
        {
            "role": "Role 1",
            "task": "01_HOOFD_099"
        },
        {
            "role": "Role 3",
            "task": "01_HOOFD_101b"
        },
        {
            "role": "Role 1",
            "task": "01_HOOFD_110_1"
        },
        {
            "role": "Role 1",
            "task": "01_HOOFD_110_2"
        },
        {
            "role": "Role 1",
            "task": "01_HOOFD_455"
        },
        {
            "role": "Role 1",
            "task": "01_HOOFD_465"
        },
        {
            "role": "Role 1",
            "task": "01_HOOFD_490_4"
        },
        {
            "role": "Role 1",
            "task": "10_UOV_060"
        },
        {
            "role": "Role 3",
            "task": "06_VD_060_1"
        },
        {
            "role": "Role 1",
            "task": "01_BB_630"
        },
        {
            "role": "Role 3",
            "task": "01_HOOFD_190"
        },
        {
            "role": "Role 1",
            "task": "09_AWB45_005"
        },
        {
            "role": "Role 1",
            "task": "01_HOOFD_510_3"
        },
        {
            "role": "Role 1",
            "task": "08_AWB45_180"
        },
        {
            "role": "Role 3",
            "task": "10_UOV_030a"
        },
        {
            "role": "Role 1",
            "task": "01_HOOFD_440_2"
        },
        {
            "role": "Role 1",
            "task": "01_BB_775"
        },
        {
            "role": "Role 6",
            "task": "08_AWB45_030"
        },
        {
            "role": "Role 1",
            "task": "08_AWB45_150"
        },
        {
            "role": "Role 1",
            "task": "01_HOOFD_205"
        },
        {
            "role": "Role 1",
            "task": "01_HOOFD_490_5"
        },
        {
            "role": "Role 2",
            "task": "01_HOOFD_090"
        },
        {
            "role": "Role 2",
            "task": "01_HOOFD_055"
        },
        {
            "role": "Role 3",
            "task": "06_VD_060_2"
        },
        {
            "role": "Role 1",
            "task": "01_HOOFD_510_4"
        },
        {
            "role": "Role 1",
            "task": "01_HOOFD_500"
        },
        {
            "role": "Role 1",
            "task": "04_BPT_010"
        },
        {
            "role": "Role 1",
            "task": "01_HOOFD_515"
        },
        {
            "role": "Role 1",
            "task": "01_HOOFD_519"
        },
        {
            "role": "Role 1",
            "task": "01_HOOFD_451"
        },
        {
            "role": "Role 1",
            "task": "04_BPT_020"
        },
        {
            "role": "Role 1",
            "task": "04_BPT_030"
        },
        {
            "role": "Role 2",
            "task": "01_HOOFD_815"
        },
        {
            "role": "Role 1",
            "task": "01_HOOFD_491"
        },
        {
            "role": "Role 2",
            "task": "01_HOOFD_814"
        },
        {
            "role": "Role 1",
            "task": "15_NGV_010"
        },
        {
            "role": "Role 1",
            "task": "01_HOOFD_061"
        },
        {
            "role": "Role 1",
            "task": "01_HOOFD_270"
        },
        {
            "role": "Role 3",
            "task": "06_VD_030_3"
        },
        {
            "role": "Role 3",
            "task": "06_VD_030_2"
        },
        {
            "role": "Role 3",
            "task": "06_VD_030_1"
        },
        {
            "role": "Role 1",
            "task": "14_VRIJ_010"
        },
        {
            "role": "Role 1",
            "task": "11_AH_II_010"
        },
        {
            "role": "Role 1",
            "task": "01_BB_730"
        },
        {
            "role": "Role 3",
            "task": "06_VD_020"
        },
        {
            "role": "Role 2",
            "task": "01_BB_765"
        },
        {
            "role": "Role 1",
            "task": "01_HOOFD_195"
        },
        {
            "role": "Role 1",
            "task": "01_HOOFD_460"
        },
        {
            "role": "Role 1",
            "task": "01_HOOFD_505"
        },
        {
            "role": "Role 1",
            "task": "01_HOOFD_470"
        },
        {
            "role": "Role 2",
            "task": "01_HOOFD_540"
        },
        {
            "role": "Role 1",
            "task": "10_UOV_035"
        },
        {
            "role": "Role 3",
            "task": "06_VD_010"
        },
        {
            "role": "Role 1",
            "task": "01_HOOFD_375"
        },
        {
            "role": "Role 1",
            "task": "01_HOOFD_370"
        },
        {
            "role": "Role 1",
            "task": "01_HOOFD_805"
        },
        {
            "role": "Role 1",
            "task": "01_HOOFD_490_1"
        },
        {
            "role": "Role 2",
            "task": "07_OPS_010"
        },
        {
            "role": "Role 1",
            "task": "01_HOOFD_011"
        },
        {
            "role": "Role 2",
            "task": "01_HOOFD_130"
        },
        {
            "role": "Role 1",
            "task": "01_HOOFD_480"
        },
        {
            "role": "Role 1",
            "task": "01_HOOFD_330"
        },
        {
            "role": "Role 1",
            "task": "01_HOOFD_260"
        },
        {
            "role": "Role 1",
            "task": "01_HOOFD_250"
        },
        {
            "role": "Role 1",
            "task": "04_BPT_005"
        },
        {
            "role": "Role 1",
            "task": "01_HOOFD_200"
        },
        {
            "role": "Role 2",
            "task": "01_HOOFD_040"
        },
        {
            "role": "Role 2",
            "task": "01_HOOFD_060"
        },
        {
            "role": "Role 2",
            "task": "08_AWB45_040"
        },
        {
            "role": "Role 1",
            "task": "09_AH_I_010"
        },
        {
            "role": "Role 1",
            "task": "02_DRZ_010"
        },
        {
            "role": "Role 1",
            "task": "01_HOOFD_430"
        },
        {
            "role": "Role 1",
            "task": "01_HOOFD_380"
        },
        {
            "role": "Role 1",
            "task": "03_GBH_005"
        },
        {
            "role": "Role 1",
            "task": "01_HOOFD_490_2"
        },
        {
            "role": "Role 2",
            "task": "05_EIND_010"
        },
        {
            "role": "Role 2",
            "task": "01_HOOFD_050"
        },
        {
            "role": "Role 1",
            "task": "01_HOOFD_490_3"
        },
        {
            "role": "Role 1",
            "task": "01_HOOFD_495"
        },
        {
            "role": "Role 1",
            "task": "10_UOV_030"
        },
        {
            "role": "Role 2",
            "task": "01_HOOFD_065_1"
        },
        {
            "role": "Role 2",
            "task": "08_AWB45_020_2"
        },
        {
            "role": "Role 2",
            "task": "01_HOOFD_120"
        },
        {
            "role": "Role 2",
            "task": "01_HOOFD_180"
        },
        {
            "role": "Role 2",
            "task": "01_HOOFD_110"
        },
        {
            "role": "Role 1",
            "task": "01_HOOFD_015"
        },
        {
            "role": "Role 1",
            "task": "01_HOOFD_030_1"
        },
        {
            "role": "Role 1",
            "task": "01_HOOFD_516"
        },
        {
            "role": "Role 1",
            "task": "01_HOOFD_020"
        },
        {
            "role": "Role 1",
            "task": "01_HOOFD_510_2"
        },
        {
            "role": "Role 1",
            "task": "01_HOOFD_030_2"
        },
        {
            "role": "Role 1",
            "task": "01_HOOFD_520"
        },
        {
            "role": "Role 1",
            "task": "01_BB_540"
        },
        {
            "role": "Role 1",
            "task": "01_HOOFD_510_1"
        },
        {
            "role": "Role 1",
            "task": "01_BB_770"
        },
        {
            "role": "Role 2",
            "task": "01_HOOFD_065_2"
        },
        {
            "role": "Role 1",
            "task": "01_HOOFD_790"
        },
        {
            "role": "Role 2",
            "task": "01_HOOFD_101"
        },
        {
            "role": "Role 1",
            "task": "01_HOOFD_800"
        },
        {
            "role": "Role 2",
            "task": "01_HOOFD_820"
        },
        {
            "role": "Role 2",
            "task": "01_HOOFD_100"
        },
        {
            "role": "Role 1",
            "task": "01_HOOFD_810"
        },
        {
            "role": "Role 1",
            "task": "01_HOOFD_530"
        },
        {
            "role": "Role 1",
            "task": "01_HOOFD_010"
        }
    ],
    "usr_index": {
        "4634935": 7,
        "560458": 2,
        "560519": 5,
        "560521": 6,
        "560528": 4,
        "560530": 3,
        "560532": 1,
        "560598": 8,
        "End": 9,
        "Start": 0
    }
}